pybyle.py
pybyle-1.0.0.dist-info/METADATA
pybyle-1.0.0.dist-info/WHEEL
pybyle-1.0.0.dist-info/RECORD
