Metadata-Version: 2.1
Name: pybyle
Version: 1.0.0
Summary: Library for simplified work with encoding
Author: Molchaliv
Author-email: molchaliv666@gmail.com
Requires-Python: >=3.10,<4.0
Classifier: Programming Language :: Python :: 3
Classifier: Programming Language :: Python :: 3.10
Classifier: Programming Language :: Python :: 3.11
